llarmy/__init__.py
llarmy/test.py
llarmy-0.0.1.dist-info/METADATA
llarmy-0.0.1.dist-info/WHEEL
llarmy-0.0.1.dist-info/licenses/LICENSE
llarmy-0.0.1.dist-info/RECORD
